{"translation": {"shortName": "NIV", "englishName": "New International Version", "licenseUrl": "https://www.biblegateway.com/versions/new-international-version-niv-bible/#copy"}, "book": {"id": "PSA", "commonName": "Psalms", "name": "Psalms"}, "numberOfVerses": 6, "chapter": {"number": 128, "content": [{"type": "verse", "number": 1, "content": ["Blessed are all who fear the Lord,\n    who walk in obedience to him."]}, {"type": "verse", "number": 2, "content": ["You will eat the fruit of your labor;\n    blessings and prosperity will be yours."]}, {"type": "verse", "number": 3, "content": ["Your wife will be like a fruitful vine\n    within your house;\nyour children will be like olive shoots\n    around your table."]}, {"type": "verse", "number": 4, "content": ["Yes, this will be the blessing\n    for the man who fears the Lord."]}, {"type": "verse", "number": 5, "content": ["May the Lord bless you from Zion;\n    may you see the prosperity of Jerusalem\n    all the days of your life."]}, {"type": "verse", "number": 6, "content": ["May you live to see your children’s children—\n    peace be on Israel."]}]}}
