{
  "version": "2026-05-01-graph-v2",
  "book": "Jeremiah",
  "chapter": 18,
  "translation": "akjv",
  "generatedAt": "2026-05-01T06:01:03.585Z",
  "themes": [
    {
      "id": "wisdom",
      "label": "Wisdom",
      "color": "#d97706",
      "tier": "Explicit",
      "summary": "This chapter points toward wisdom, understanding, discernment, counsel, or instruction. Local Strong’s word study and cross references data reinforce this reading across 7 verses. Commentary leans on \"Jerome on Commentary on Jeremiah: (Verse 18) And they said: Come, let us devise schemes again...\". Word-study detail reinforces \"מֵֽחָכָ֔ם: from the wise - wise, (i.e., intelligent, skilful or artful)\".",
      "supportingVerses": [
        1,
        2,
        3,
        5,
        6,
        18,
        23
      ],
      "versePhrases": {
        "1": [
          "The word which came to Jeremiah from the Lord, saying,"
        ],
        "2": [
          "Arise, and go down to the potter’s house, and there..."
        ],
        "3": [
          "Then I went down to the potter’s house, and, behold,..."
        ],
        "5": [
          "Then the word of the Lord came to me, saying,"
        ],
        "6": [
          "O house of Israel, cannot I do with you as..."
        ],
        "18": [
          "wise",
          "counsel"
        ],
        "23": [
          "counsel"
        ]
      },
      "evidenceTrail": [
        {
          "kind": "commentary",
          "label": "Verse 1 commentary",
          "detail": "Prophetic introduction formulas pervade the prophetic books, authenticating messages as divin...",
          "anchorVerse": 1
        },
        {
          "kind": "historical_commentary",
          "label": "Verse 1 historical",
          "detail": "Jerome on Commentary on Jeremiah: (Chapter XVIII — Verses 1-6) The word that came to Jeremiah...",
          "anchorVerse": 1
        },
        {
          "kind": "commentary",
          "label": "Verse 2 commentary",
          "detail": "How does God's use of familiar imagery to communicate profound truth demonstrate His wisdom a...",
          "anchorVerse": 2
        },
        {
          "kind": "historical_commentary",
          "label": "Verse 2 historical",
          "detail": "Jerome on Commentary on Jeremiah: (Chapter XVIII — Verses 1-6) The word that came to Jeremiah...",
          "anchorVerse": 2
        }
      ]
    },
    {
      "id": "creation",
      "label": "Creation",
      "color": "#0f766e",
      "tier": "Explicit",
      "summary": "This chapter underscores creation, the heavens and earth, or God’s creative ordering work. Local Strong’s word study and cross references data reinforce this reading across 4 verses. Commentary leans on \"Tyrannius Rufinus on COMMENTARY ON THE APOSTLES' CREED 29: By his passion, therefore, Christ...\". Word-study detail reinforces \"מַ֛יִם: waters - water; figuratively, juice; by euphemism, urine, semen\".",
      "supportingVerses": [
        1,
        4,
        6,
        14
      ],
      "versePhrases": {
        "1": [
          "The word which came to Jeremiah from the Lord, saying,"
        ],
        "4": [
          "made"
        ],
        "6": [
          "O house of Israel, cannot I do with you as..."
        ],
        "14": [
          "waters"
        ]
      },
      "evidenceTrail": [
        {
          "kind": "commentary",
          "label": "Verse 1 commentary",
          "detail": "How does Christ as the Word made flesh fulfill and complete God's prophetic revelation?",
          "anchorVerse": 1
        },
        {
          "kind": "historical_commentary",
          "label": "Verse 1 historical",
          "detail": "Jerome on Commentary on Jeremiah: (Chapter XVIII — Verses 1-6) The word that came to Jeremiah...",
          "anchorVerse": 1
        },
        {
          "kind": "commentary",
          "label": "Verse 4 commentary",
          "detail": "The crucial observation: \"the vessel that he made of clay was marred in the hand of the potte...",
          "anchorVerse": 4
        },
        {
          "kind": "historical_commentary",
          "label": "Verse 4 historical",
          "detail": "Tyrannius Rufinus on COMMENTARY ON THE APOSTLES' CREED 29: By his passion, therefore, Christ...",
          "anchorVerse": 4
        }
      ]
    },
    {
      "id": "judgment",
      "label": "Judgment",
      "color": "#b91c1c",
      "tier": "Strong",
      "summary": "This chapter addresses wrath, judgment, condemnation, justice, or divine reckoning. Local Strong’s word study and cross references data reinforce this reading across 12 verses. Commentary leans on \"Tertullian on AGAINST MARCION 2.24: I affirm that “wickedness” in this context does not signi...\". Cross references echo \"Judgment\".",
      "supportingVerses": [
        3,
        4,
        6,
        7,
        8,
        10,
        11,
        13,
        17,
        19,
        20,
        21
      ],
      "versePhrases": {
        "3": [
          "Then I went down to the potter’s house, and, behold,..."
        ],
        "4": [
          "And the vessel that he made of clay was marred..."
        ],
        "6": [
          "O house of Israel, cannot I do with you as..."
        ],
        "7": [
          "At what instant I shall speak concerning a nation, and..."
        ],
        "8": [
          "if that nation, against whom I have pronounced, turn from..."
        ],
        "10": [
          "if it do evil in my sight, that it obey..."
        ],
        "11": [
          "Now therefore go to, speak to the men of Judah,..."
        ],
        "13": [
          "Therefore thus saith the Lord"
        ],
        "17": [
          "I will scatter them as with an east wind before..."
        ],
        "19": [
          "Give heed to me, O Lord, and hearken to the..."
        ],
        "20": [
          "wrath"
        ],
        "21": [
          "Therefore deliver up their children to the famine, and pour..."
        ]
      },
      "evidenceTrail": [
        {
          "kind": "commentary",
          "label": "Verse 3 commentary",
          "detail": "Jeremiah obeys: \"Then I went down to the potter's house.\" His immediate compliance models pro...",
          "anchorVerse": 3
        },
        {
          "kind": "historical_commentary",
          "label": "Verse 3 historical",
          "detail": "Jerome on SIX BOOKS ON JEREMIAH 4:2.4-7: Whatever is discerned by the eyes arrives to the jud...",
          "anchorVerse": 3
        },
        {
          "kind": "commentary",
          "label": "Verse 4 commentary",
          "detail": "The crucial observation: \"the vessel that he made of clay was marred in the hand of the potte...",
          "anchorVerse": 4
        },
        {
          "kind": "historical_commentary",
          "label": "Verse 4 historical",
          "detail": "Jerome on SIX BOOKS ON JEREMIAH 4:2.4-7: Whatever is discerned by the eyes arrives to the jud...",
          "anchorVerse": 4
        }
      ]
    },
    {
      "id": "grace",
      "label": "Grace/Mercy",
      "color": "#2563eb",
      "tier": "Strong",
      "summary": "This chapter highlights undeserved favor, mercy, forgiveness, compassion, or pardon. Local Strong’s word study and cross references data reinforce this reading across 7 verses. Commentary leans on \"Jerome on St. Jerome, Commentary on Daniel, CHAPTER FOUR: [Daniel 4:27] \"'Wherefore, O king,...\". Word-study detail reinforces \"תְּכַפֵּר֙: me forgive - to cover (specifically with bitumen)\".",
      "supportingVerses": [
        6,
        8,
        9,
        10,
        20,
        21,
        23
      ],
      "versePhrases": {
        "6": [
          "O house of Israel, cannot I do with you as..."
        ],
        "8": [
          "if that nation, against whom I have pronounced, turn from..."
        ],
        "9": [
          "And at what instant I shall speak concerning a nation,..."
        ],
        "10": [
          "if it do evil in my sight, that it obey..."
        ],
        "20": [
          "Shall evil be recompensed for good"
        ],
        "21": [
          "Therefore deliver up their children to the famine, and pour..."
        ],
        "23": [
          "forgive"
        ]
      },
      "evidenceTrail": [
        {
          "kind": "commentary",
          "label": "Verse 6 commentary",
          "detail": "This verse contains God's response to the potter's house lesson (vv. 1-5). God declares His s...",
          "anchorVerse": 6
        },
        {
          "kind": "historical_commentary",
          "label": "Verse 6 historical",
          "detail": "John Chrysostom on INSTRUCTIONS TO CATECHUMENS 1:4: When, therefore, God speaks of an irremed...",
          "anchorVerse": 6
        },
        {
          "kind": "commentary",
          "label": "Verse 8 commentary",
          "detail": "The crucial qualification: \"If that nation, against whom I have pronounced, turn from their e...",
          "anchorVerse": 8
        },
        {
          "kind": "historical_commentary",
          "label": "Verse 8 historical",
          "detail": "Jerome on St. Jerome, Commentary on Daniel, CHAPTER FOUR: [Daniel 4:27] \"'Wherefore, O king,...",
          "anchorVerse": 8
        }
      ]
    },
    {
      "id": "guidance",
      "label": "Guidance",
      "color": "#0369a1",
      "tier": "Strong",
      "summary": "This chapter emphasizes leading, direction, teaching, or the path God sets before His people. Local Strong’s word study and cross references data reinforce this reading across 4 verses. Commentary leans on \"Jerome on Commentary on Jeremiah: (Verse 18) And they said: Come, let us devise schemes again...\". Word-study detail reinforces \"וְעֵצָה֙: nor counsel - advice; by implication, plan; also prudence\".",
      "supportingVerses": [
        15,
        18,
        19,
        23
      ],
      "versePhrases": {
        "15": [
          "and they have caused them to stumble in their ways from the ancient paths"
        ],
        "18": [
          "counsel"
        ],
        "19": [
          "Give heed to me, O Lord, and hearken to the..."
        ],
        "23": [
          "counsel"
        ]
      },
      "evidenceTrail": [
        {
          "kind": "commentary",
          "label": "Verse 15 commentary",
          "detail": "The indictment: \"Because my people hath forgotten me, they have burned incense to vanity.\" \"F...",
          "anchorVerse": 15
        },
        {
          "kind": "historical_commentary",
          "label": "Verse 15 historical",
          "detail": "Jerome on Commentary on Jeremiah: (Verse 15) Because my people have forgotten me, offering sa...",
          "anchorVerse": 15
        },
        {
          "kind": "commentary",
          "label": "Verse 18 commentary",
          "detail": "The conspirators' plot: \"Then said they, Come, and let us devise devices against Jeremiah.\" T...",
          "anchorVerse": 18
        },
        {
          "kind": "historical_commentary",
          "label": "Verse 18 historical",
          "detail": "Jerome on Commentary on Jeremiah: (Verse 18) And they said: Come, let us devise schemes again...",
          "anchorVerse": 18
        }
      ]
    },
    {
      "id": "salvation",
      "label": "Salvation",
      "color": "#0284c7",
      "tier": "Strong",
      "summary": "This chapter speaks of rescue, deliverance, redemption, life, or being saved. Local Strong’s word study and cross references data reinforce this reading across 3 verses. Commentary leans on \"Theodoret of Cyrus on ON JEREMIAH 4:18.7-8: Do not despair of salvation, God is saying. Even...\". Word-study detail reinforces \"תֵּ֨ן: Therefore deliver up - to give, used with greatest latitude of application (put, make,...\".",
      "supportingVerses": [
        8,
        12,
        21
      ],
      "versePhrases": {
        "8": [
          "if that nation, against whom I have pronounced, turn from..."
        ],
        "12": [
          "And they said, There is no hope"
        ],
        "21": [
          "deliver"
        ]
      },
      "evidenceTrail": [
        {
          "kind": "commentary",
          "label": "Verse 8 commentary",
          "detail": "The crucial qualification: \"If that nation, against whom I have pronounced, turn from their e...",
          "anchorVerse": 8
        },
        {
          "kind": "historical_commentary",
          "label": "Verse 8 historical",
          "detail": "Theodoret of Cyrus on ON JEREMIAH 4:18.7-8: Do not despair of salvation, God is saying. Even...",
          "anchorVerse": 8
        },
        {
          "kind": "commentary",
          "label": "Verse 12 commentary",
          "detail": "Judah's defiant response: \"And they said, There is no hope: but we will walk after our own de...",
          "anchorVerse": 12
        },
        {
          "kind": "historical_commentary",
          "label": "Verse 12 historical",
          "detail": "Jerome on Commentary on Jeremiah: (Verse 12) But they say, That is in vain! We will follow ou...",
          "anchorVerse": 12
        }
      ]
    }
  ]
}
