{
  "version": "2026-05-01-graph-v2",
  "book": "Esther",
  "chapter": 5,
  "translation": "amp",
  "generatedAt": "2026-05-01T05:46:15.137Z",
  "themes": [
    {
      "id": "kingdom",
      "label": "Kingdom",
      "color": "#1d4ed8",
      "tier": "Explicit",
      "summary": "This chapter stresses reign, kingdom, throne, rule, or the authority of God and His Christ. Local Strong’s word study and cross references data reinforce this reading across 13 verses. Commentary leans on \"Esther's approach: 'And it was so, when the king saw Esther the queen standing in the court,...\". Cross references echo \"Kingdom\".",
      "supportingVerses": [
        1,
        2,
        3,
        4,
        5,
        6,
        7,
        8,
        9,
        11,
        12,
        13,
        14
      ],
      "versePhrases": {
        "1": [
          "king",
          "throne"
        ],
        "2": [
          "king",
          "scepter"
        ],
        "3": [
          "kingdom",
          "king"
        ],
        "4": [
          "king"
        ],
        "5": [
          "king"
        ],
        "6": [
          "kingdom",
          "king"
        ],
        "7": [
          "Then Esther replied, “My petition and my request is this"
        ],
        "8": [
          "king"
        ],
        "9": [
          "king"
        ],
        "11": [
          "king"
        ],
        "12": [
          "king"
        ],
        "13": [
          "king"
        ],
        "14": [
          "king"
        ]
      },
      "evidenceTrail": [
        {
          "kind": "cross_reference",
          "label": "Kingdom",
          "detail": "Esther 6:4",
          "anchorVerse": 1,
          "referenceLabel": "Esther 6:4"
        },
        {
          "kind": "commentary",
          "label": "Verse 1 commentary",
          "detail": "Esther's approach to the king 'on the third day' wearing royal robes demonstrates both courag...",
          "anchorVerse": 1
        },
        {
          "kind": "historical_commentary",
          "label": "Verse 1 historical",
          "detail": "Rabanus Maurus on Commentary on Esther: What can it mean that on the third day Esther dressed...",
          "anchorVerse": 1
        },
        {
          "kind": "strongs",
          "label": "Verse 1 word study",
          "detail": "וְ֠הַמֶּלֶךְ: and the king - a king",
          "anchorVerse": 1
        }
      ]
    },
    {
      "id": "prayer",
      "label": "Prayer",
      "color": "#7c3aed",
      "tier": "Explicit",
      "summary": "This chapter centers on prayer, calling on God, supplication, or worshipful petition. Local Strong’s word study and cross references data reinforce this reading across 4 verses. Commentary leans on \"When called to risky obedience, do I seek God in prayer before acting, trusting outcomes to Him?\". Word-study detail reinforces \"שְׁאֵֽלָתִ֖י: My petition - a petition; by implication, a loan\".",
      "supportingVerses": [
        1,
        6,
        7,
        8
      ],
      "versePhrases": {
        "1": [
          "On the third day [of the fast] Esther put on..."
        ],
        "6": [
          "petition"
        ],
        "7": [
          "petition"
        ],
        "8": [
          "petition"
        ]
      },
      "evidenceTrail": [
        {
          "kind": "commentary",
          "label": "Verse 1 commentary",
          "detail": "When called to risky obedience, do I seek God in prayer before acting, trusting outcomes to Him?",
          "anchorVerse": 1
        },
        {
          "kind": "historical_commentary",
          "label": "Verse 1 historical",
          "detail": "Rabanus Maurus on Commentary on Esther: What can it mean that on the third day Esther dressed...",
          "anchorVerse": 1
        },
        {
          "kind": "commentary",
          "label": "Verse 6 commentary",
          "detail": "And the king said unto Esther at the banquet of wine, What is thy petition? and it shall be g...",
          "anchorVerse": 6
        },
        {
          "kind": "historical_commentary",
          "label": "Verse 6 historical",
          "detail": "Rabanus Maurus on EXPLANATION ON THE BOOK OF ESTHER 8: This postponement of the petition is n...",
          "anchorVerse": 6
        }
      ]
    },
    {
      "id": "creation",
      "label": "Creation",
      "color": "#0f766e",
      "tier": "Strong",
      "summary": "This chapter underscores creation, the heavens and earth, or God’s creative ordering work. Local Strong’s word study and cross references data reinforce this reading across 2 verses. Commentary leans on \"Rabanus Maurus on EXPLANATION ON THE BOOK OF ESTHER 8: He, who held out to that queen the gol...\".",
      "supportingVerses": [
        2,
        14
      ],
      "versePhrases": {
        "2": [
          "When the king saw Esther the queen standing in the..."
        ],
        "14": [
          "made"
        ]
      },
      "evidenceTrail": [
        {
          "kind": "commentary",
          "label": "Verse 2 commentary",
          "detail": "Persian court protocol made unsummoned approach to the king capital offense unless he extende...",
          "anchorVerse": 2
        },
        {
          "kind": "historical_commentary",
          "label": "Verse 2 historical",
          "detail": "Rabanus Maurus on EXPLANATION ON THE BOOK OF ESTHER 8: He, who held out to that queen the gol...",
          "anchorVerse": 2
        },
        {
          "kind": "commentary",
          "label": "Verse 14 commentary",
          "detail": "Then said Zeresh his wife and all his friends unto him, Let a gallows be made of fifty cubits...",
          "anchorVerse": 14
        }
      ]
    },
    {
      "id": "fear",
      "label": "Fear/Anxiety",
      "color": "#dc2626",
      "tier": "Strong",
      "summary": "This chapter deals with fear, dread, anxiety, alarm, or the call not to be afraid. Local Strong’s word study and cross references data reinforce this reading across 1 verse. Word-study detail reinforces \"זָ֣ע: nor moved - properly, to shake off, i.e., (figuratively) to agitate (as with fear)\".",
      "supportingVerses": [
        9
      ],
      "versePhrases": {
        "9": [
          "fear"
        ]
      },
      "evidenceTrail": [
        {
          "kind": "strongs",
          "label": "Verse 9 word study",
          "detail": "זָ֣ע: nor moved - properly, to shake off, i.e., (figuratively) to agitate (as with fear)",
          "anchorVerse": 9
        }
      ]
    },
    {
      "id": "worship",
      "label": "Worship",
      "color": "#ca8a04",
      "tier": "Strong",
      "summary": "This chapter gives prominence to praise, worship, thanksgiving, or blessing God’s name. Local Strong’s word study and cross references data reinforce this reading across 1 verse. Commentary leans on \"And Haman told them of the glory of his riches, and the multitude of his children, and all th...\". Cross references echo \"Glory\".",
      "supportingVerses": [
        11
      ],
      "versePhrases": {
        "11": [
          "glory"
        ]
      },
      "evidenceTrail": [
        {
          "kind": "cross_reference",
          "label": "Glory",
          "detail": "Genesis 31:1",
          "anchorVerse": 11,
          "referenceLabel": "Genesis 31:1"
        },
        {
          "kind": "commentary",
          "label": "Verse 11 commentary",
          "detail": "And Haman told them of the glory of his riches, and the multitude of his children, and all th...",
          "anchorVerse": 11
        },
        {
          "kind": "strongs",
          "label": "Verse 11 word study",
          "detail": "כְּב֥וֹד: them of the glory - properly, weight, but only figuratively in a good sense, splend...",
          "anchorVerse": 11
        }
      ]
    }
  ]
}
