{
  "version": "2026-05-01-graph-v2",
  "book": "Acts",
  "chapter": 2,
  "translation": "amp",
  "generatedAt": "2026-05-01T05:48:50.773Z",
  "themes": [
    {
      "id": "spirit",
      "label": "Spirit",
      "color": "#8b5cf6",
      "tier": "Explicit",
      "summary": "This chapter highlights the Spirit’s presence, power, leading, or inner witness. Local Strong’s word study and cross references data reinforce this reading across 17 verses. Commentary leans on \"Theophylact of Ohrid on Commentary on Acts: \"Divided tongues, as of fire.\" The Lord, who suff...\". Cross references echo \"Spirit\".",
      "supportingVerses": [
        2,
        3,
        4,
        5,
        6,
        13,
        16,
        17,
        18,
        20,
        31,
        33,
        37,
        38,
        39,
        41,
        44
      ],
      "versePhrases": {
        "2": [
          "wind"
        ],
        "3": [
          "Spirit",
          "Holy Spirit"
        ],
        "4": [
          "Spirit",
          "Holy Spirit"
        ],
        "5": [
          "Now there were Jews living in Jerusalem, devout and God-fearing..."
        ],
        "6": [
          "And when this sound was heard, a crowd gathered, and..."
        ],
        "13": [
          "But others were laughing and joking and ridiculing them, saying,..."
        ],
        "16": [
          "but this is [the beginning of] what was spoken of..."
        ],
        "17": [
          "Spirit"
        ],
        "18": [
          "Spirit"
        ],
        "20": [
          "‘The sun shall be turned into darkness And the moon..."
        ],
        "31": [
          "he foresaw and spoke [prophetically] of the resurrection of the..."
        ],
        "33": [
          "Spirit",
          "Holy Spirit"
        ],
        "37": [
          "Now when they heard this, they were cut to the..."
        ],
        "38": [
          "Spirit",
          "Holy Spirit"
        ],
        "39": [
          "Spirit",
          "Holy Spirit"
        ],
        "41": [
          "So then, those who accepted his message were baptized"
        ],
        "44": [
          "And all those who had believed [in Jesus as Savior]..."
        ]
      },
      "evidenceTrail": [
        {
          "kind": "commentary",
          "label": "Verse 2 commentary",
          "detail": "A sound from heaven as of a rushing mighty wind —The Greek 'ēchos' (sound) and 'pheromenēs pn...",
          "anchorVerse": 2
        },
        {
          "kind": "historical_commentary",
          "label": "Verse 2 historical",
          "detail": "Bede on Retractions on Acts: And suddenly there came from heaven a sound as of a violent rush...",
          "anchorVerse": 2
        },
        {
          "kind": "strongs",
          "label": "Verse 2 word study",
          "detail": "πνοῆς: wind - respiration, a breeze",
          "anchorVerse": 2
        },
        {
          "kind": "commentary",
          "label": "Verse 3 commentary",
          "detail": "The 'cloven tongues like as of fire' (Greek: diamerizomenai glōssai hōsei pyros) represent th...",
          "anchorVerse": 3
        }
      ]
    },
    {
      "id": "salvation",
      "label": "Salvation",
      "color": "#0284c7",
      "tier": "Explicit",
      "summary": "This chapter speaks of rescue, deliverance, redemption, life, or being saved. Local Strong’s word study and cross references data reinforce this reading across 10 verses. Commentary leans on \"Augustine of Hippo on Letter 164 (A.D. 414), Sections 2, 3, 6, 8, 10: After having said that...\". Cross references echo \"Salvation\".",
      "supportingVerses": [
        19,
        20,
        21,
        22,
        23,
        24,
        33,
        39,
        40,
        47
      ],
      "versePhrases": {
        "19": [
          "‘And I will bring about wonders in the sky above..."
        ],
        "20": [
          "‘The sun shall be turned into darkness And the moon..."
        ],
        "21": [
          "saved"
        ],
        "22": [
          "“Men of Israel, listen to these words"
        ],
        "23": [
          "this Man, when handed over [to the Roman authorities] according..."
        ],
        "24": [
          "But God raised Him up, releasing Him and bringing an..."
        ],
        "33": [
          "Therefore having been exalted to the right hand of God,..."
        ],
        "39": [
          "For the promise [of the Holy Spirit] is for you..."
        ],
        "40": [
          "saved"
        ],
        "47": [
          "saved"
        ]
      },
      "evidenceTrail": [
        {
          "kind": "commentary",
          "label": "Verse 19 commentary",
          "detail": "What does cosmic upheaval accompanying salvation history teach about God's lordship over all...",
          "anchorVerse": 19
        },
        {
          "kind": "historical_commentary",
          "label": "Verse 19 historical",
          "detail": "Bede on Commentary on Acts: Blood and fire and vapor of smoke. The blood of the Lord’s side,...",
          "anchorVerse": 19
        },
        {
          "kind": "commentary",
          "label": "Verse 20 commentary",
          "detail": "The Day of the Lord - 'great and notable' (Greek 'epiphane', shining forth) - represents both...",
          "anchorVerse": 20
        },
        {
          "kind": "historical_commentary",
          "label": "Verse 20 historical",
          "detail": "Oecumenius on Commentary on Acts: Now, \"The sun shall be turned into darkness,\" and the prece...",
          "anchorVerse": 20
        }
      ]
    },
    {
      "id": "covenant",
      "label": "Covenant",
      "color": "#a16207",
      "tier": "Explicit",
      "summary": "This chapter points to covenant, promise, oath, inheritance, or the enduring faithfulness of God. Local Strong’s word study and cross references data reinforce this reading across 10 verses. Commentary leans on \"Theophylact of Ohrid on Commentary on Acts: \"God promised with an oath.\" He did not say \"prom...\". Cross references echo \"Covenant\".",
      "supportingVerses": [
        1,
        2,
        4,
        16,
        17,
        18,
        30,
        33,
        38,
        39
      ],
      "versePhrases": {
        "1": [
          "When the day of Pentecost had come, they were all..."
        ],
        "2": [
          "and suddenly a sound came from heaven like a rushing..."
        ],
        "4": [
          "And they were all filled [that is, diffused throughout their..."
        ],
        "16": [
          "but this is [the beginning of] what was spoken of..."
        ],
        "17": [
          "‘And it shall be in the last days,’ says God,..."
        ],
        "18": [
          "Even on My bond-servants, both men and women, I will..."
        ],
        "30": [
          "oath"
        ],
        "33": [
          "promise",
          "blessing"
        ],
        "38": [
          "And Peter said to them, “Repent [change your old way..."
        ],
        "39": [
          "promise"
        ]
      },
      "evidenceTrail": [
        {
          "kind": "commentary",
          "label": "Verse 1 commentary",
          "detail": "When the day of Pentecost was fully come (ἐν τῷ συμπληροῦσθαι)—The timing was sovereignly app...",
          "anchorVerse": 1
        },
        {
          "kind": "historical_commentary",
          "label": "Verse 1 historical",
          "detail": "Leo the Great on SERMON 75: To the Hebrew people, now freed from Egypt, the law was given on...",
          "anchorVerse": 1
        },
        {
          "kind": "commentary",
          "label": "Verse 2 commentary",
          "detail": "How does Pentecost as New Covenant inauguration compare with Sinai's Old Covenant giving?",
          "anchorVerse": 2
        },
        {
          "kind": "historical_commentary",
          "label": "Verse 2 historical",
          "detail": "Cyril of Jerusalem on Catechetical Lecture 17.15: And lest people should be ignorant of the g...",
          "anchorVerse": 2
        }
      ]
    },
    {
      "id": "righteousness",
      "label": "Righteousness",
      "color": "#1d4ed8",
      "tier": "Explicit",
      "summary": "This chapter presses into righteousness, justice, uprightness, or holy living before God. Local Strong’s word study and cross references data reinforce this reading across 10 verses. Commentary leans on \"Theophylact of Ohrid on Commentary on Acts: \"Divided tongues, as of fire.\" The Lord, who suff...\". Cross references echo \"Holy\".",
      "supportingVerses": [
        2,
        3,
        4,
        22,
        24,
        27,
        33,
        38,
        39,
        43
      ],
      "versePhrases": {
        "2": [
          "and suddenly a sound came from heaven like a rushing..."
        ],
        "3": [
          "Holy"
        ],
        "4": [
          "Holy"
        ],
        "22": [
          "just"
        ],
        "24": [
          "But God raised Him up, releasing Him and bringing an..."
        ],
        "27": [
          "Holy"
        ],
        "33": [
          "Holy"
        ],
        "38": [
          "Holy"
        ],
        "39": [
          "Holy"
        ],
        "43": [
          "A sense of awe was felt by everyone, and many..."
        ]
      },
      "evidenceTrail": [
        {
          "kind": "historical_commentary",
          "label": "Verse 2 historical",
          "detail": "Gregory the Dialogist on Forty Gospel Homilies, Homily 30: For today the Holy Spirit came upo...",
          "anchorVerse": 2
        },
        {
          "kind": "strongs",
          "label": "Verse 2 word study",
          "detail": "ὥσπερ: as - just as, i.e., exactly like",
          "anchorVerse": 2
        },
        {
          "kind": "commentary",
          "label": "Verse 3 commentary",
          "detail": "The 'cloven tongues like as of fire' (Greek: diamerizomenai glōssai hōsei pyros) represent th...",
          "anchorVerse": 3
        },
        {
          "kind": "historical_commentary",
          "label": "Verse 3 historical",
          "detail": "Theophylact of Ohrid on Commentary on Acts: \"Divided tongues, as of fire.\" The Lord, who suff...",
          "anchorVerse": 3
        }
      ]
    },
    {
      "id": "creation",
      "label": "Creation",
      "color": "#0f766e",
      "tier": "Explicit",
      "summary": "This chapter underscores creation, the heavens and earth, or God’s creative ordering work. Local Strong’s word study and cross references data reinforce this reading across 8 verses. Commentary leans on \"Hippolytus of Rome on Dubious and Spurious Pieces: For at that time the trumpet shall sound,...\". Word-study detail reinforces \"ἥλιος: The sun - the sun; by implication, light\".",
      "supportingVerses": [
        1,
        9,
        11,
        19,
        20,
        28,
        34,
        36
      ],
      "versePhrases": {
        "1": [
          "When the day of Pentecost had come, they were all..."
        ],
        "9": [
          "[Among us there are] Parthians, Medes and Elamites, and people..."
        ],
        "11": [
          "Cretans and Arabs—we all hear them speaking in our [native]..."
        ],
        "19": [
          "earth"
        ],
        "20": [
          "‘The sun shall be turned into darkness And the moon..."
        ],
        "28": [
          "made"
        ],
        "34": [
          "heavens"
        ],
        "36": [
          "made"
        ]
      },
      "evidenceTrail": [
        {
          "kind": "commentary",
          "label": "Verse 1 commentary",
          "detail": "Pentecost was the Feast of Weeks, celebrating wheat harvest and (in Jewish tradition) commemo...",
          "anchorVerse": 1
        },
        {
          "kind": "historical_commentary",
          "label": "Verse 1 historical",
          "detail": "John Chrysostom on Homily on Acts 4: Dost thou perceive the type? What is this Pentecost? The...",
          "anchorVerse": 1
        },
        {
          "kind": "commentary",
          "label": "Verse 9 commentary",
          "detail": "This geographic catalog demonstrates the fulfillment of Acts 1:8's commission - 'unto the utt...",
          "anchorVerse": 9
        },
        {
          "kind": "historical_commentary",
          "label": "Verse 9 historical",
          "detail": "John Chrysostom on Homily on Acts 4: This nerved the Apostles: for, what it was to speak in t...",
          "anchorVerse": 9
        }
      ]
    },
    {
      "id": "holiness",
      "label": "Holiness",
      "color": "#4338ca",
      "tier": "Explicit",
      "summary": "This chapter focuses on holiness, righteousness, purity, consecration, or being set apart. Local Strong’s word study and cross references data reinforce this reading across 8 verses. Commentary leans on \"Theophylact of Ohrid on Commentary on Acts: \"Divided tongues, as of fire.\" The Lord, who suff...\". Cross references echo \"Holy\".",
      "supportingVerses": [
        3,
        4,
        24,
        27,
        33,
        38,
        39,
        46
      ],
      "versePhrases": {
        "3": [
          "Holy"
        ],
        "4": [
          "Holy"
        ],
        "24": [
          "But God raised Him up, releasing Him and bringing an..."
        ],
        "27": [
          "Holy"
        ],
        "33": [
          "Holy"
        ],
        "38": [
          "Holy"
        ],
        "39": [
          "Holy"
        ],
        "46": [
          "Day after day they met in the temple [area] continuing..."
        ]
      },
      "evidenceTrail": [
        {
          "kind": "commentary",
          "label": "Verse 3 commentary",
          "detail": "The 'cloven tongues like as of fire' (Greek: diamerizomenai glōssai hōsei pyros) represent th...",
          "anchorVerse": 3
        },
        {
          "kind": "historical_commentary",
          "label": "Verse 3 historical",
          "detail": "Theophylact of Ohrid on Commentary on Acts: \"Divided tongues, as of fire.\" The Lord, who suff...",
          "anchorVerse": 3
        },
        {
          "kind": "cross_reference",
          "label": "Holy",
          "detail": "Acts 13:52",
          "anchorVerse": 4,
          "referenceLabel": "Acts 13:52"
        },
        {
          "kind": "commentary",
          "label": "Verse 4 commentary",
          "detail": "Filled with the Holy Ghost (ἐπλήσθησαν πνεύματος ἁγίου)—The aorist passive verb indicates God...",
          "anchorVerse": 4
        }
      ]
    }
  ]
}
