{
  "version": "2026-05-01-graph-v2",
  "book": "Joshua",
  "chapter": 13,
  "translation": "csb",
  "generatedAt": "2026-05-01T05:42:23.870Z",
  "themes": [
    {
      "id": "covenant",
      "label": "Covenant",
      "color": "#a16207",
      "tier": "Explicit",
      "summary": "This chapter points to covenant, promise, oath, inheritance, or the enduring faithfulness of God. Local Strong’s word study and cross references data reinforce this reading across 10 verses. Commentary leans on \"And Moses gave unto the tribe of the children of Reuben inheritance according to their famili...\". Word-study detail reinforces \"נַֽחֲלָתָ֑ם: their inheritance - properly, something inherited, i.e., (abstractly) occupancy,...\".",
      "supportingVerses": [
        2,
        6,
        7,
        8,
        14,
        15,
        23,
        24,
        28,
        33
      ],
      "versePhrases": {
        "2": [
          "This is the land that remains"
        ],
        "6": [
          "inheritance"
        ],
        "7": [
          "inheritance"
        ],
        "8": [
          "inheritance"
        ],
        "14": [
          "promised",
          "inheritance"
        ],
        "15": [
          "To the tribe of Reuben’s descendants by their clans, Moses..."
        ],
        "23": [
          "inheritance"
        ],
        "24": [
          "To the tribe of the Gadites by their clans, Moses..."
        ],
        "28": [
          "inheritance"
        ],
        "33": [
          "promised",
          "inheritance"
        ]
      },
      "evidenceTrail": [
        {
          "kind": "commentary",
          "label": "Verse 2 commentary",
          "detail": "God identifies remaining unconquered territory: 'all the borders of the Philistines, and all...",
          "anchorVerse": 2
        },
        {
          "kind": "historical_commentary",
          "label": "Verse 2 historical",
          "detail": "Origen of Alexandria on HOMILIES ON JOSHUA 16.3: But follow me, O hearer, through delicate th...",
          "anchorVerse": 2
        },
        {
          "kind": "commentary",
          "label": "Verse 6 commentary",
          "detail": "All the inhabitants of the hill country from Lebanon unto Misrephothmaim, and all the Sidonia...",
          "anchorVerse": 6
        },
        {
          "kind": "strongs",
          "label": "Verse 6 word study",
          "detail": "בְּֽנַחֲלָ֔ה: for an inheritance - properly, something inherited, i.e., (abstractly) occupanc...",
          "anchorVerse": 6
        }
      ]
    },
    {
      "id": "kingdom",
      "label": "Kingdom",
      "color": "#1d4ed8",
      "tier": "Explicit",
      "summary": "This chapter stresses reign, kingdom, throne, rule, or the authority of God and His Christ. Local Strong’s word study and cross references data reinforce this reading across 8 verses. Commentary leans on \"And all the cities of the plain, and all the kingdom of Sihon king of the Amorites —This vers...\". Cross references echo \"Kingdom\".",
      "supportingVerses": [
        2,
        10,
        12,
        21,
        22,
        27,
        30,
        31
      ],
      "versePhrases": {
        "2": [
          "This is the land that remains"
        ],
        "10": [
          "King"
        ],
        "12": [
          "kingdom"
        ],
        "21": [
          "kingdom",
          "King"
        ],
        "22": [
          "Along with those the Israelites put to death, they also..."
        ],
        "27": [
          "kingdom",
          "King"
        ],
        "30": [
          "kingdom",
          "King"
        ],
        "31": [
          "But half of Gilead, and Og’s royal cities in Bashan—Ashtaroth..."
        ]
      },
      "evidenceTrail": [
        {
          "kind": "commentary",
          "label": "Verse 2 commentary",
          "detail": "The Philistines occupied the coastal plain (later called Philistia) in five major cities: Gaz...",
          "anchorVerse": 2
        },
        {
          "kind": "historical_commentary",
          "label": "Verse 2 historical",
          "detail": "Origen of Alexandria on HOMILIES ON JOSHUA 16.3: But follow me, O hearer, through delicate th...",
          "anchorVerse": 2
        },
        {
          "kind": "commentary",
          "label": "Verse 10 commentary",
          "detail": "And all the cities of Sihon king of the Amorites, which reigned in Heshbon, unto the border o...",
          "anchorVerse": 10
        },
        {
          "kind": "strongs",
          "label": "Verse 10 word study",
          "detail": "מֶ֣לֶךְ: king - a king",
          "anchorVerse": 10
        }
      ]
    },
    {
      "id": "righteousness",
      "label": "Righteousness",
      "color": "#1d4ed8",
      "tier": "Explicit",
      "summary": "This chapter presses into righteousness, justice, uprightness, or holy living before God. Local Strong’s word study and cross references data reinforce this reading across 3 verses. Commentary leans on \"The practical arrangements for Levitical support involved multiple mechanisms: tithes of prod...\".",
      "supportingVerses": [
        8,
        14,
        33
      ],
      "versePhrases": {
        "8": [
          "just"
        ],
        "14": [
          "just"
        ],
        "33": [
          "just"
        ]
      },
      "evidenceTrail": [
        {
          "kind": "commentary",
          "label": "Verse 14 commentary",
          "detail": "The practical arrangements for Levitical support involved multiple mechanisms: tithes of prod...",
          "anchorVerse": 14
        }
      ]
    },
    {
      "id": "provision",
      "label": "Provision",
      "color": "#d97706",
      "tier": "Strong",
      "summary": "This chapter emphasizes God’s supplying care, nourishment, sufficiency, or generous provision. Local Strong’s word study and cross references data reinforce this reading across 4 verses. Commentary leans on \"In what areas of Christian life do we need to balance trusting God's sovereignty (\"I will dri...\". Word-study detail reinforces \"בְּֽנַחֲלָ֔ה: for an inheritance - properly, something inherited, i.e., (abstractly) occupanc...\".",
      "supportingVerses": [
        6,
        14,
        28,
        33
      ],
      "versePhrases": {
        "6": [
          "all the inhabitants of the hill country from Lebanon to..."
        ],
        "14": [
          "He did not, however, give any inheritance to the tribe..."
        ],
        "28": [
          "This was the inheritance of the Gadites by their clans,..."
        ],
        "33": [
          "portion"
        ]
      },
      "evidenceTrail": [
        {
          "kind": "commentary",
          "label": "Verse 6 commentary",
          "detail": "In what areas of Christian life do we need to balance trusting God's sovereignty (\"I will dri...",
          "anchorVerse": 6
        },
        {
          "kind": "strongs",
          "label": "Verse 6 word study",
          "detail": "בְּֽנַחֲלָ֔ה: for an inheritance - properly, something inherited, i.e., (abstractly) occupanc...",
          "anchorVerse": 6
        },
        {
          "kind": "commentary",
          "label": "Verse 14 commentary",
          "detail": "The practical arrangements for Levitical support involved multiple mechanisms: tithes of prod...",
          "anchorVerse": 14
        },
        {
          "kind": "strongs",
          "label": "Verse 14 word study",
          "detail": "נַֽחֲלָת֔וֹ: are their inheritance - properly, something inherited, i.e., (abstractly) occupa...",
          "anchorVerse": 14
        }
      ]
    },
    {
      "id": "peace",
      "label": "Peace/Rest",
      "color": "#4f46e5",
      "tier": "Strong",
      "summary": "This chapter offers peace, rest, stillness, comfort, or settled safety in God. Local Strong’s word study and cross references data reinforce this reading across 3 verses. Commentary leans on \"The practical arrangements for Levitical support involved multiple mechanisms: tithes of prod...\". Word-study detail reinforces \"יֶ֚תֶר: the rest - properly, an overhanging, i.e., (by implication) a small rope (as hanging...\".",
      "supportingVerses": [
        13,
        14,
        27
      ],
      "versePhrases": {
        "13": [
          "still"
        ],
        "14": [
          "He did not, however, give any inheritance to the tribe..."
        ],
        "27": [
          "rest"
        ]
      },
      "evidenceTrail": [
        {
          "kind": "commentary",
          "label": "Verse 13 commentary",
          "detail": "Geshur became a minor kingdom that maintained independence throughout Israel's history. King...",
          "anchorVerse": 13
        },
        {
          "kind": "strongs",
          "label": "Verse 13 word study",
          "detail": "וַיֵּ֨שֶׁב: dwell - properly, to sit down (specifically as judge. in ambush, in quiet); by im...",
          "anchorVerse": 13
        },
        {
          "kind": "commentary",
          "label": "Verse 14 commentary",
          "detail": "The practical arrangements for Levitical support involved multiple mechanisms: tithes of prod...",
          "anchorVerse": 14
        },
        {
          "kind": "historical_commentary",
          "label": "Verse 14 historical",
          "detail": "Origen of Alexandria on HOMILIES ON JOSHUA 17.2: Neither Moses nor Jesus [Joshua], however, g...",
          "anchorVerse": 14
        }
      ]
    },
    {
      "id": "creation",
      "label": "Creation",
      "color": "#0f766e",
      "tier": "Strong",
      "summary": "This chapter underscores creation, the heavens and earth, or God’s creative ordering work. Local Strong’s word study and cross references data reinforce this reading across 2 verses. Commentary leans on \"Only unto the tribe of Levi he gave none inheritance; the sacrifices of the LORD God of Israe...\". Word-study detail reinforces \"אֶ֖רֶץ: the land - the earth (at large, or partitively a land)\".",
      "supportingVerses": [
        14,
        25
      ],
      "versePhrases": {
        "14": [
          "made"
        ],
        "25": [
          "this as their territory"
        ]
      },
      "evidenceTrail": [
        {
          "kind": "commentary",
          "label": "Verse 14 commentary",
          "detail": "Only unto the tribe of Levi he gave none inheritance; the sacrifices of the LORD God of Israe...",
          "anchorVerse": 14
        },
        {
          "kind": "strongs",
          "label": "Verse 14 word study",
          "detail": "אִשֵּׁ֨י: made by fire - properly, a burnt-offering; but occasionally of any sacrifice",
          "anchorVerse": 14
        },
        {
          "kind": "commentary",
          "label": "Verse 25 commentary",
          "detail": "Gilead was prized for its balm (Jeremiah 8:22, 46:11), a medicinal resin exported throughout...",
          "anchorVerse": 25
        },
        {
          "kind": "strongs",
          "label": "Verse 25 word study",
          "detail": "אֶ֖רֶץ: the land - the earth (at large, or partitively a land)",
          "anchorVerse": 25
        }
      ]
    }
  ]
}
