{
  "version": "2026-05-01-graph-v2",
  "book": "1 Corinthians",
  "chapter": 15,
  "translation": "esv",
  "generatedAt": "2026-05-01T05:55:44.633Z",
  "themes": [
    {
      "id": "faith",
      "label": "Faith/Belief",
      "color": "#0f4fcf",
      "tier": "Explicit",
      "summary": "This chapter emphasizes trust, belief, confidence, or steadfast reliance on God. Local Strong’s word study and cross references data reinforce this reading across 25 verses. Commentary leans on \"Thomas Aquinas on Commentary on 1 Corinthians: 1023. – Then when he says, Therefore my belove...\". Cross references echo \"Hope\".",
      "supportingVerses": [
        1,
        2,
        3,
        6,
        7,
        9,
        11,
        13,
        14,
        15,
        17,
        18,
        19,
        20,
        23,
        29,
        30,
        31,
        32,
        33,
        34,
        38,
        48,
        54,
        58
      ],
      "versePhrases": {
        "1": [
          "Now I would remind you, brothers, of the gospel I..."
        ],
        "2": [
          "if you hold fast to the word I preached to you—unless you believed in vain"
        ],
        "3": [
          "For I delivered to you as of first importance what..."
        ],
        "6": [
          "Then he appeared to more than five hundred brothers at..."
        ],
        "7": [
          "Then he appeared to James, then to all the apostles"
        ],
        "9": [
          "For I am the least of the apostles, unworthy to..."
        ],
        "11": [
          "so we preach and so you believed"
        ],
        "13": [
          "But if there is no resurrection of the dead, then..."
        ],
        "14": [
          "faith"
        ],
        "15": [
          "We are even found to be misrepresenting God, because we..."
        ],
        "17": [
          "faith"
        ],
        "18": [
          "Then those also who have fallen asleep in Christ have..."
        ],
        "19": [
          "hope"
        ],
        "20": [
          "But in fact Christ has been raised from the dead,..."
        ],
        "23": [
          "But each in his own order"
        ],
        "29": [
          "Otherwise, what do people mean by being baptized on behalf..."
        ],
        "30": [
          "Why are we in danger every hour"
        ],
        "31": [
          "I protest, brothers, by my pride in you, which I..."
        ],
        "32": [
          "What do I gain if, humanly speaking, I fought with..."
        ],
        "33": [
          "Do not be deceived"
        ],
        "34": [
          "Wake up from your drunken stupor, as is right, and..."
        ],
        "38": [
          "But God gives it a body as he has chosen,..."
        ],
        "48": [
          "As was the man of dust, so also are those..."
        ],
        "54": [
          "When the perishable puts on the imperishable, and the mortal..."
        ],
        "58": [
          "steadfast"
        ]
      },
      "evidenceTrail": [
        {
          "kind": "commentary",
          "label": "Verse 1 commentary",
          "detail": "What does it mean that you 'stand' in the gospel—how does resurrection truth provide stabilit...",
          "anchorVerse": 1
        },
        {
          "kind": "historical_commentary",
          "label": "Verse 1 historical",
          "detail": "Thomas Aquinas on Commentary on 1 Corinthians: 888. – After instructing the Corinthians about...",
          "anchorVerse": 1
        },
        {
          "kind": "cross_reference",
          "label": "Faith",
          "detail": "Colossians 1:23",
          "anchorVerse": 2,
          "referenceLabel": "Colossians 1:23"
        },
        {
          "kind": "commentary",
          "label": "Verse 2 commentary",
          "detail": "By which also ye are saved (δι' οὗ καὶ σῴζεσθε, di' hou kai sōzesthe )—The present tense verb...",
          "anchorVerse": 2
        }
      ]
    },
    {
      "id": "worship",
      "label": "Worship",
      "color": "#ca8a04",
      "tier": "Explicit",
      "summary": "This chapter gives prominence to praise, worship, thanksgiving, or blessing God’s name. Local Strong’s word study and cross references data reinforce this reading across 9 verses. Commentary leans on \"John Chrysostom on Homily on 1 Corinthians 41: \"There are also celestial bodies, and bodies t...\". Cross references echo \"Glory\".",
      "supportingVerses": [
        28,
        30,
        32,
        39,
        40,
        41,
        43,
        49,
        57
      ],
      "versePhrases": {
        "28": [
          "When all things are subjected to him, then the Son..."
        ],
        "30": [
          "Why are we in danger every hour"
        ],
        "32": [
          "What do I gain if, humanly speaking, I fought with..."
        ],
        "39": [
          "For not all flesh is the same, but there is..."
        ],
        "40": [
          "glory"
        ],
        "41": [
          "glory"
        ],
        "43": [
          "glory"
        ],
        "49": [
          "Just as we have borne the image of the man..."
        ],
        "57": [
          "thanks"
        ]
      },
      "evidenceTrail": [
        {
          "kind": "commentary",
          "label": "Verse 28 commentary",
          "detail": "And when all things shall be subdued unto him (ὅταν δὲ ὑποταγῇ αὐτῷ τὰ πάντα)—The aorist pass...",
          "anchorVerse": 28
        },
        {
          "kind": "historical_commentary",
          "label": "Verse 28 historical",
          "detail": "Augustine of Hippo on City of God 22.30: God will be the consummation of all our desiring—the...",
          "anchorVerse": 28
        },
        {
          "kind": "commentary",
          "label": "Verse 30 commentary",
          "detail": "And why stand we in jeopardy every hour? (τί καὶ ἡμεῖς κινδυνεύομεν πᾶσαν ὥραν;)—Paul shifts...",
          "anchorVerse": 30
        },
        {
          "kind": "historical_commentary",
          "label": "Verse 30 historical",
          "detail": "John Chrysostom on Homily on 1 Corinthians 40: \"Why do we also stand in jeopardy every hour?...",
          "anchorVerse": 30
        }
      ]
    },
    {
      "id": "kingdom",
      "label": "Kingdom",
      "color": "#1d4ed8",
      "tier": "Explicit",
      "summary": "This chapter stresses reign, kingdom, throne, rule, or the authority of God and His Christ. Local Strong’s word study and cross references data reinforce this reading across 5 verses. Commentary leans on \"Thomas Aquinas on Commentary on 1 Corinthians: 940. – For he must reign. Here the Apostle sho...\". Cross references echo \"Kingdom\".",
      "supportingVerses": [
        24,
        25,
        27,
        50,
        55
      ],
      "versePhrases": {
        "24": [
          "kingdom"
        ],
        "25": [
          "reign"
        ],
        "27": [
          "For “God has put all things in subjection under his..."
        ],
        "50": [
          "kingdom"
        ],
        "55": [
          "“O death, where is your victory"
        ]
      },
      "evidenceTrail": [
        {
          "kind": "cross_reference",
          "label": "Kingdom",
          "detail": "Daniel 7:27",
          "anchorVerse": 24,
          "referenceLabel": "Daniel 7:27"
        },
        {
          "kind": "commentary",
          "label": "Verse 24 commentary",
          "detail": "Then cometh the end (εἶτα τὸ τέλος)—The word telos (τέλος) means \"end, goal, completion, cons...",
          "anchorVerse": 24
        },
        {
          "kind": "historical_commentary",
          "label": "Verse 24 historical",
          "detail": "John Chrysostom on Homily on 1 Corinthians 39: \"Then cometh the end.\" For when these shall ha...",
          "anchorVerse": 24
        },
        {
          "kind": "strongs",
          "label": "Verse 24 word study",
          "detail": "βασιλείαν: the kingdom - properly, royalty, i.e., (abstractly) rule, or (concretely) a realm...",
          "anchorVerse": 24
        }
      ]
    },
    {
      "id": "grace",
      "label": "Grace/Mercy",
      "color": "#2563eb",
      "tier": "Explicit",
      "summary": "This chapter highlights undeserved favor, mercy, forgiveness, compassion, or pardon. Local Strong’s word study and cross references data reinforce this reading across 4 verses. Commentary leans on \"But by the grace of God I am what I am (χάριτι δὲ θεοῦ εἰμι ὅ εἰμι)—This phrase echoes God's...\". Cross references echo \"Grace\".",
      "supportingVerses": [
        9,
        10,
        47,
        57
      ],
      "versePhrases": {
        "9": [
          "For I am the least of the apostles, unworthy to..."
        ],
        "10": [
          "grace"
        ],
        "47": [
          "The first man was from the earth, a man of..."
        ],
        "57": [
          "But thanks be to God, who gives us the victory..."
        ]
      },
      "evidenceTrail": [
        {
          "kind": "commentary",
          "label": "Verse 9 commentary",
          "detail": "Why doesn't Paul's past disqualify him—what does this teach about grace and calling?",
          "anchorVerse": 9
        },
        {
          "kind": "historical_commentary",
          "label": "Verse 9 historical",
          "detail": "Thomas Aquinas on Commentary on 1 Corinthians: 905. – And therefore, as though assigning a re...",
          "anchorVerse": 9
        },
        {
          "kind": "cross_reference",
          "label": "Grace",
          "detail": "Romans 12:3",
          "anchorVerse": 10,
          "referenceLabel": "Romans 12:3"
        },
        {
          "kind": "commentary",
          "label": "Verse 10 commentary",
          "detail": "But by the grace of God I am what I am (χάριτι δὲ θεοῦ εἰμι ὅ εἰμι)—This phrase echoes God's...",
          "anchorVerse": 10
        }
      ]
    },
    {
      "id": "new-birth",
      "label": "New Birth",
      "color": "#7c3aed",
      "tier": "Explicit",
      "summary": "This chapter emphasizes regeneration, new life, spiritual birth, or becoming God’s children. Local Strong’s word study and cross references data reinforce this reading across 4 verses. Commentary leans on \"Theophylact of Ohrid on Commentary on 1 Corinthians: The solution is borrowed from what is ob...\". Word-study detail reinforces \"ζῳοποιηθήσονται: be made alive - to (re-)vitalize (literally or figuratively)\".",
      "supportingVerses": [
        6,
        22,
        36,
        51
      ],
      "versePhrases": {
        "6": [
          "alive"
        ],
        "22": [
          "alive",
          "made alive"
        ],
        "36": [
          "You foolish person! What you sow does not come to life unless it dies"
        ],
        "51": [
          "Behold"
        ]
      },
      "evidenceTrail": [
        {
          "kind": "historical_commentary",
          "label": "Verse 6 historical",
          "detail": "Shepherd of Hermas on Shepherd of Hermas, Vision 3: Those square white stones which fitted ex...",
          "anchorVerse": 6
        },
        {
          "kind": "commentary",
          "label": "Verse 22 commentary",
          "detail": "For as in Adam all die (ὥσπερ γὰρ ἐν τῷ Ἀδὰμ πάντες ἀποθνῄσκουσιν)—The phrase en tō Adam (\"in...",
          "anchorVerse": 22
        },
        {
          "kind": "historical_commentary",
          "label": "Verse 22 historical",
          "detail": "Thomas Aquinas on Commentary on 1 Corinthians: 932. – For as in Adam. Here he proves the same...",
          "anchorVerse": 22
        },
        {
          "kind": "strongs",
          "label": "Verse 22 word study",
          "detail": "ζῳοποιηθήσονται: be made alive - to (re-)vitalize (literally or figuratively)",
          "anchorVerse": 22
        }
      ]
    },
    {
      "id": "truth",
      "label": "Truth",
      "color": "#0f4fcf",
      "tier": "Strong",
      "summary": "This chapter brings truth, faithfulness, revelation, or the trustworthiness of God into focus. Local Strong’s word study and cross references data reinforce this reading across 21 verses. Commentary leans on \"Theophylact of Ohrid on Commentary on 1 Corinthians: Whether I labored more or they did, yet...\". Word-study detail reinforces \"πλανᾶσθε·: Be - to (properly, cause to) roam (from safety, truth, or virtue)\".",
      "supportingVerses": [
        3,
        4,
        5,
        8,
        11,
        12,
        15,
        18,
        19,
        20,
        26,
        27,
        33,
        36,
        43,
        45,
        47,
        50,
        51,
        52,
        54
      ],
      "versePhrases": {
        "3": [
          "For I delivered to you as of first importance what..."
        ],
        "4": [
          "that he was buried, that he was raised on the..."
        ],
        "5": [
          "and that he appeared to Cephas, then to the twelve"
        ],
        "8": [
          "Last of all, as to one untimely born, he appeared..."
        ],
        "11": [
          "Whether then it was I or they, so we preach..."
        ],
        "12": [
          "Now if Christ is proclaimed as raised from the dead,..."
        ],
        "15": [
          "true"
        ],
        "18": [
          "Then those also who have fallen asleep in Christ have..."
        ],
        "19": [
          "If in Christ we have hope in this life only,..."
        ],
        "20": [
          "But in fact Christ has been raised from the dead,..."
        ],
        "26": [
          "The last enemy to be destroyed is death"
        ],
        "27": [
          "For “God has put all things in subjection under his..."
        ],
        "33": [
          "Do not be deceived"
        ],
        "36": [
          "You foolish person"
        ],
        "43": [
          "It is sown in dishonor"
        ],
        "45": [
          "Thus it is written, “The first man Adam became a..."
        ],
        "47": [
          "The first man was from the earth, a man of..."
        ],
        "50": [
          "I tell you this, brothers"
        ],
        "51": [
          "Behold"
        ],
        "52": [
          "in a moment, in the twinkling of an eye, at..."
        ],
        "54": [
          "When the perishable puts on the imperishable, and the mortal..."
        ]
      },
      "evidenceTrail": [
        {
          "kind": "commentary",
          "label": "Verse 3 commentary",
          "detail": "What significance does the early date of this creed have for the reliability of resurrection...",
          "anchorVerse": 3
        },
        {
          "kind": "historical_commentary",
          "label": "Verse 3 historical",
          "detail": "John Chrysostom on Homily on 1 Corinthians 38: \"For I delivered unto you first of all that wh...",
          "anchorVerse": 3
        },
        {
          "kind": "commentary",
          "label": "Verse 4 commentary",
          "detail": "Jewish burial customs involved immediate entombment and three-day observation to confirm deat...",
          "anchorVerse": 4
        },
        {
          "kind": "historical_commentary",
          "label": "Verse 4 historical",
          "detail": "Thomas Aquinas on Commentary on 1 Corinthians: 896. – I delivered to you, secondly, the buria...",
          "anchorVerse": 4
        }
      ]
    }
  ]
}
