{
  "version": "2026-05-01-graph-v2",
  "book": "1 Samuel",
  "chapter": 4,
  "translation": "niv",
  "generatedAt": "2026-05-01T05:49:37.712Z",
  "themes": [
    {
      "id": "covenant",
      "label": "Covenant",
      "color": "#a16207",
      "tier": "Explicit",
      "summary": "This chapter points to covenant, promise, oath, inheritance, or the enduring faithfulness of God. Local Strong’s word study and cross references data reinforce this reading across 3 verses. Commentary leans on \"Bede on Commentary on Samuel: Why has the Lord struck us down today before the Philistines? e...\". Word-study detail reinforces \"בְּרִית: of the covenant - a compact (because made by passing between pieces of flesh)\".",
      "supportingVerses": [
        3,
        4,
        5
      ],
      "versePhrases": {
        "3": [
          "covenant"
        ],
        "4": [
          "covenant"
        ],
        "5": [
          "covenant"
        ]
      },
      "evidenceTrail": [
        {
          "kind": "commentary",
          "label": "Verse 3 commentary",
          "detail": "The Ark's military function in Israel's early history (crossing Jordan, conquering Jericho) c...",
          "anchorVerse": 3
        },
        {
          "kind": "historical_commentary",
          "label": "Verse 3 historical",
          "detail": "Bede on Commentary on Samuel: Why has the Lord struck us down today before the Philistines? e...",
          "anchorVerse": 3
        },
        {
          "kind": "strongs",
          "label": "Verse 3 word study",
          "detail": "בְּרִ֣ית: of the covenant - a compact (because made by passing between pieces of flesh)",
          "anchorVerse": 3
        },
        {
          "kind": "commentary",
          "label": "Verse 4 commentary",
          "detail": "The Ark's arrival with Hophni and Phinehas - the very priests under judgment - seals Israel's...",
          "anchorVerse": 4
        }
      ]
    },
    {
      "id": "presence",
      "label": "Presence",
      "color": "#2563eb",
      "tier": "Strong",
      "summary": "This chapter highlights God’s nearness, abiding presence, indwelling, or covenant companionship. Local Strong’s word study and cross references data reinforce this reading across 6 verses. Commentary leans on \"Gregory the Dialogist on Commentary on 1 Kings, Book 3, Chapter 2: 26. But who was the daught...\". Word-study detail reinforces \"אֶל: - near, with or among; often in general, to\".",
      "supportingVerses": [
        2,
        3,
        4,
        11,
        19,
        21
      ],
      "versePhrases": {
        "2": [
          "The Philistines deployed their forces to meet Israel, and as..."
        ],
        "3": [
          "with us"
        ],
        "4": [
          "were there with the ark of the covenant of God"
        ],
        "11": [
          "The ark of God was captured, and Eli’s two sons,..."
        ],
        "19": [
          "near"
        ],
        "21": [
          "She named the boy Ichabod, saying, “The Glory has departed..."
        ]
      },
      "evidenceTrail": [
        {
          "kind": "commentary",
          "label": "Verse 2 commentary",
          "detail": "The Ark of the Covenant represented God's throne and presence among His people. Its associati...",
          "anchorVerse": 2
        },
        {
          "kind": "historical_commentary",
          "label": "Verse 2 historical",
          "detail": "Bede on Commentary on Samuel: When the battle began, Israel turned their backs to the Philist...",
          "anchorVerse": 2
        },
        {
          "kind": "commentary",
          "label": "Verse 3 commentary",
          "detail": "The Ark's military function in Israel's early history (crossing Jordan, conquering Jericho) c...",
          "anchorVerse": 3
        },
        {
          "kind": "strongs",
          "label": "Verse 3 word study",
          "detail": "אֶל: - near, with or among; often in general, to",
          "anchorVerse": 3
        }
      ]
    },
    {
      "id": "salvation",
      "label": "Salvation",
      "color": "#0284c7",
      "tier": "Strong",
      "summary": "This chapter speaks of rescue, deliverance, redemption, life, or being saved. Local Strong’s word study and cross references data reinforce this reading across 5 verses. Commentary leans on \"Gregory the Dialogist on Commentary on 1 Kings, Book 3, Chapter 2: 6. This is certainly the p...\". Word-study detail reinforces \"יַצִּילֵ֔נוּ: unto us! who shall deliver - to snatch away, whether in a good or a bad sense\".",
      "supportingVerses": [
        2,
        3,
        4,
        8,
        10
      ],
      "versePhrases": {
        "2": [
          "The Philistines deployed their forces to meet Israel, and as..."
        ],
        "3": [
          "save"
        ],
        "4": [
          "So the people sent men to Shiloh, and they brought..."
        ],
        "8": [
          "deliver"
        ],
        "10": [
          "So the Philistines fought, and the Israelites were defeated and..."
        ]
      },
      "evidenceTrail": [
        {
          "kind": "commentary",
          "label": "Verse 2 commentary",
          "detail": "The initial defeat - four thousand Israelites killed - prompts self-examination. The elders'...",
          "anchorVerse": 2
        },
        {
          "kind": "historical_commentary",
          "label": "Verse 2 historical",
          "detail": "Gregory the Dialogist on Commentary on 1 Kings, Book 3, Chapter 2: 1. The blessed Apostle sho...",
          "anchorVerse": 2
        },
        {
          "kind": "commentary",
          "label": "Verse 3 commentary",
          "detail": "The elders' statement reveals both right and wrong. Rightly, they acknowledge the LORD 'smote...",
          "anchorVerse": 3
        },
        {
          "kind": "historical_commentary",
          "label": "Verse 3 historical",
          "detail": "Bede on Commentary on Samuel: Why has the Lord struck us down today before the Philistines? e...",
          "anchorVerse": 3
        }
      ]
    },
    {
      "id": "fear",
      "label": "Fear/Anxiety",
      "color": "#dc2626",
      "tier": "Strong",
      "summary": "This chapter deals with fear, dread, anxiety, alarm, or the call not to be afraid. Local Strong’s word study and cross references data reinforce this reading across 3 verses. Commentary leans on \"Gregory the Dialogist on Commentary on 1 Kings, Book 3, Chapter 2: 26. But who was the daught...\". Word-study detail reinforces \"וַיִּֽרְאוּ֙: were afraid - to fear; morally to revere; causatively to frighten\".",
      "supportingVerses": [
        6,
        7,
        20
      ],
      "versePhrases": {
        "6": [
          "Hearing the uproar, the Philistines asked, “What’s all this shouting..."
        ],
        "7": [
          "afraid"
        ],
        "20": [
          "As she was dying, the women attending her said, “Don’t..."
        ]
      },
      "evidenceTrail": [
        {
          "kind": "commentary",
          "label": "Verse 6 commentary",
          "detail": "What do the Philistines' fear and eventual victory teach about spiritual reality versus reput...",
          "anchorVerse": 6
        },
        {
          "kind": "historical_commentary",
          "label": "Verse 6 historical",
          "detail": "Gregory the Dialogist on Commentary on 1 Kings, Book 3, Chapter 2: 8. Indeed the Philistines...",
          "anchorVerse": 6
        },
        {
          "kind": "commentary",
          "label": "Verse 7 commentary",
          "detail": "Philistine fear intensifies: 'Woe unto us! for there hath not been such a thing heretofore.'...",
          "anchorVerse": 7
        },
        {
          "kind": "historical_commentary",
          "label": "Verse 7 historical",
          "detail": "Bede on Commentary on Samuel: And the Philistines were afraid, saying, \"God has come into the...",
          "anchorVerse": 7
        }
      ]
    },
    {
      "id": "worship",
      "label": "Worship",
      "color": "#ca8a04",
      "tier": "Strong",
      "summary": "This chapter gives prominence to praise, worship, thanksgiving, or blessing God’s name. Local Strong’s word study and cross references data reinforce this reading across 3 verses. Commentary leans on \"Gregory the Dialogist on Commentary on 1 Kings, Book 3, Chapter 2: 27. The ark indeed is capt...\". Cross references echo \"Glory\".",
      "supportingVerses": [
        20,
        21,
        22
      ],
      "versePhrases": {
        "20": [
          "As she was dying, the women attending her said, “Don’t..."
        ],
        "21": [
          "Glory"
        ],
        "22": [
          "Glory"
        ]
      },
      "evidenceTrail": [
        {
          "kind": "commentary",
          "label": "Verse 20 commentary",
          "detail": "As she dies, attendants try to comfort her: 'Fear not; for thou hast born a son.' In normal c...",
          "anchorVerse": 20
        },
        {
          "kind": "historical_commentary",
          "label": "Verse 20 historical",
          "detail": "Gregory the Dialogist on Commentary on 1 Kings, Book 3, Chapter 2: 26. But who was the daught...",
          "anchorVerse": 20
        },
        {
          "kind": "strongs",
          "label": "Verse 20 word study",
          "detail": "עָֽנְתָ֖ה: But she answered - properly, to eye or (generally) to heed, i.e., pay attention; b...",
          "anchorVerse": 20
        },
        {
          "kind": "cross_reference",
          "label": "Glory",
          "detail": "Psalms 78:61",
          "anchorVerse": 21,
          "referenceLabel": "Psalms 78:61"
        }
      ]
    },
    {
      "id": "guidance",
      "label": "Guidance",
      "color": "#0369a1",
      "tier": "Strong",
      "summary": "This chapter emphasizes leading, direction, teaching, or the path God sets before His people. Local Strong’s word study and cross references data reinforce this reading across 2 verses. Commentary leans on \"Gregory the Dialogist on Commentary on 1 Kings, Book 3, Chapter 2: 1. The blessed Apostle sho...\".",
      "supportingVerses": [
        2,
        18
      ],
      "versePhrases": {
        "2": [
          "The Philistines deployed their forces to meet Israel, and as..."
        ],
        "18": [
          "led"
        ]
      },
      "evidenceTrail": [
        {
          "kind": "commentary",
          "label": "Verse 2 commentary",
          "detail": "The Ark of the Covenant represented God's throne and presence among His people. Its associati...",
          "anchorVerse": 2
        },
        {
          "kind": "historical_commentary",
          "label": "Verse 2 historical",
          "detail": "Gregory the Dialogist on Commentary on 1 Kings, Book 3, Chapter 2: 1. The blessed Apostle sho...",
          "anchorVerse": 2
        },
        {
          "kind": "historical_commentary",
          "label": "Verse 18 historical",
          "detail": "Gregory the Dialogist on Commentary on 1 Kings, Book 3, Chapter 2: 22. What is it that Eli, u...",
          "anchorVerse": 18
        }
      ]
    }
  ]
}
