{
  "version": "2026-05-01-graph-v2",
  "book": "1 Samuel",
  "chapter": 17,
  "translation": "niv",
  "generatedAt": "2026-05-01T05:49:39.590Z",
  "themes": [
    {
      "id": "salvation",
      "label": "Salvation",
      "color": "#0284c7",
      "tier": "Strong",
      "summary": "This chapter speaks of rescue, deliverance, redemption, life, or being saved. Local Strong’s word study and cross references data reinforce this reading across 12 verses. Commentary leans on \"David said moreover, The LORD that delivered me out of the paw of the lion, and out of the pa...\". Word-study detail reinforces \"יְסַגֶּרְךָ֩: deliver - to shut up; figuratively, to surrender\".",
      "supportingVerses": [
        6,
        14,
        17,
        22,
        24,
        25,
        31,
        35,
        36,
        37,
        43,
        46
      ],
      "versePhrases": {
        "6": [
          "on his legs he wore bronze greaves, and a bronze..."
        ],
        "14": [
          "David was the youngest"
        ],
        "17": [
          "Now Jesse said to his son David, “Take this ephah..."
        ],
        "22": [
          "David left his things with the keeper of supplies, ran..."
        ],
        "24": [
          "Whenever the Israelites saw the man, they all fled from..."
        ],
        "25": [
          "Now the Israelites had been saying, “Do you see how..."
        ],
        "31": [
          "What David said was overheard and reported to Saul, and..."
        ],
        "35": [
          "struck it and rescued the sheep from its mouth"
        ],
        "36": [
          "Your servant has killed both the lion and the bear"
        ],
        "37": [
          "rescue"
        ],
        "43": [
          "He said to David, “Am I a dog, that you..."
        ],
        "46": [
          "deliver"
        ]
      },
      "evidenceTrail": [
        {
          "kind": "commentary",
          "label": "Verse 6 commentary",
          "detail": "How does this passage connect to the larger biblical narrative of redemption and point toward...",
          "anchorVerse": 6
        },
        {
          "kind": "historical_commentary",
          "label": "Verse 6 historical",
          "detail": "Bede on Commentary on Samuel: And he had bronze greaves on his legs, etc. Helmet, mail, shiel...",
          "anchorVerse": 6
        },
        {
          "kind": "commentary",
          "label": "Verse 14 commentary",
          "detail": "How does this passage connect to the larger biblical narrative of redemption and point toward...",
          "anchorVerse": 14
        },
        {
          "kind": "historical_commentary",
          "label": "Verse 14 historical",
          "detail": "Bede on Commentary on Samuel: David, however, was the youngest. The Lord is to be understood...",
          "anchorVerse": 14
        }
      ]
    },
    {
      "id": "presence",
      "label": "Presence",
      "color": "#2563eb",
      "tier": "Strong",
      "summary": "This chapter highlights God’s nearness, abiding presence, indwelling, or covenant companionship. Local Strong’s word study and cross references data reinforce this reading across 5 verses. Commentary leans on \"And he took his staff in his hand, and chose him five smooth stones out of the brook, and put...\". Word-study detail reinforces \"וְקָרֵ֖ב: and drew near - near\".",
      "supportingVerses": [
        26,
        28,
        37,
        40,
        41
      ],
      "versePhrases": {
        "26": [
          "near"
        ],
        "28": [
          "heard him speaking with the men"
        ],
        "37": [
          "with you"
        ],
        "40": [
          "with his sling in his hand"
        ],
        "41": [
          "with his shield bearer in front of him"
        ]
      },
      "evidenceTrail": [
        {
          "kind": "strongs",
          "label": "Verse 26 word study",
          "detail": "אֶֽל: - near, with or among; often in general, to",
          "anchorVerse": 26
        },
        {
          "kind": "commentary",
          "label": "Verse 28 commentary",
          "detail": "Elder brothers held authority in Israelite family structure. Eliab may have still smarted fro...",
          "anchorVerse": 28
        },
        {
          "kind": "historical_commentary",
          "label": "Verse 28 historical",
          "detail": "Bede on Commentary on Samuel: Why, he says, have you come? etc. Let the Jews be angry with Ch...",
          "anchorVerse": 28
        },
        {
          "kind": "strongs",
          "label": "Verse 28 word study",
          "detail": "אֶל: - near, with or among; often in general, to",
          "anchorVerse": 28
        }
      ]
    },
    {
      "id": "kingdom",
      "label": "Kingdom",
      "color": "#1d4ed8",
      "tier": "Strong",
      "summary": "This chapter stresses reign, kingdom, throne, rule, or the authority of God and His Christ. Local Strong’s word study and cross references data reinforce this reading across 3 verses. Commentary leans on \"And the king said, Enquire thou whose son the stripling is. The term 'stripling' ( 'elem ) de...\". Word-study detail reinforces \"הַמֶּ֑לֶךְ: And the king - a king\".",
      "supportingVerses": [
        25,
        56,
        58
      ],
      "versePhrases": {
        "25": [
          "king"
        ],
        "56": [
          "king"
        ],
        "58": [
          "“Whose son are you, young man"
        ]
      },
      "evidenceTrail": [
        {
          "kind": "commentary",
          "label": "Verse 25 commentary",
          "detail": "And the men of Israel said, Have ye seen this man that is come up? surely to defy Israel is h...",
          "anchorVerse": 25
        },
        {
          "kind": "historical_commentary",
          "label": "Verse 25 historical",
          "detail": "Bede on Commentary on Samuel: Therefore, the man who strikes him, the king will enrich, etc....",
          "anchorVerse": 25
        },
        {
          "kind": "strongs",
          "label": "Verse 25 word study",
          "detail": "הַמֶּ֣לֶךְ׀: him the king - a king",
          "anchorVerse": 25
        },
        {
          "kind": "commentary",
          "label": "Verse 56 commentary",
          "detail": "And the king said, Enquire thou whose son the stripling is. The term 'stripling' ( 'elem ) de...",
          "anchorVerse": 56
        }
      ]
    },
    {
      "id": "guidance",
      "label": "Guidance",
      "color": "#0369a1",
      "tier": "Strong",
      "summary": "This chapter emphasizes leading, direction, teaching, or the path God sets before His people. Local Strong’s word study and cross references data reinforce this reading across 3 verses. Commentary leans on \"And he took his staff in his hand, and chose him five smooth stones out of the brook, and put...\". Word-study detail reinforces \"הָֽרֹעִ֧ים: them in a shepherd's - to tend a flock; i.e., pasture it; intransitively, to graz...\".",
      "supportingVerses": [
        20,
        40,
        49
      ],
      "versePhrases": {
        "20": [
          "shepherd"
        ],
        "40": [
          "shepherd"
        ],
        "49": [
          "Reaching into his bag and taking out a stone, he..."
        ]
      },
      "evidenceTrail": [
        {
          "kind": "commentary",
          "label": "Verse 20 commentary",
          "detail": "And David rose up early in the morning, and left the sheep with a keeper, and took, and went,...",
          "anchorVerse": 20
        },
        {
          "kind": "commentary",
          "label": "Verse 40 commentary",
          "detail": "And he took his staff in his hand, and chose him five smooth stones out of the brook, and put...",
          "anchorVerse": 40
        },
        {
          "kind": "historical_commentary",
          "label": "Verse 40 historical",
          "detail": "Bede on Commentary on Samuel: And he chose for himself five smooth stones from the brook, etc...",
          "anchorVerse": 40
        },
        {
          "kind": "strongs",
          "label": "Verse 40 word study",
          "detail": "הָֽרֹעִ֧ים: them in a shepherd's - to tend a flock; i.e., pasture it; intransitively, to graz...",
          "anchorVerse": 40
        }
      ]
    },
    {
      "id": "fear",
      "label": "Fear/Anxiety",
      "color": "#dc2626",
      "tier": "Strong",
      "summary": "This chapter deals with fear, dread, anxiety, alarm, or the call not to be afraid. Local Strong’s word study and cross references data reinforce this reading across 2 verses. Commentary leans on \"When Saul and all Israel heard those words of the Philistine, they were dismayed, and greatly...\". Word-study detail reinforces \"וַיִּֽרְא֖וּ: afraid - to fear; morally to revere; causatively to frighten\".",
      "supportingVerses": [
        11,
        24
      ],
      "versePhrases": {
        "11": [
          "dismayed"
        ],
        "24": [
          "fear"
        ]
      },
      "evidenceTrail": [
        {
          "kind": "commentary",
          "label": "Verse 11 commentary",
          "detail": "When Saul and all Israel heard those words of the Philistine, they were dismayed, and greatly...",
          "anchorVerse": 11
        },
        {
          "kind": "strongs",
          "label": "Verse 11 word study",
          "detail": "וַיִּֽרְא֖וּ: afraid - to fear; morally to revere; causatively to frighten",
          "anchorVerse": 11
        },
        {
          "kind": "commentary",
          "label": "Verse 24 commentary",
          "detail": "And all the men of Israel, when they saw the man, fled from him, and were sore afraid. The Go...",
          "anchorVerse": 24
        },
        {
          "kind": "historical_commentary",
          "label": "Verse 24 historical",
          "detail": "Bede on Commentary on Samuel: And all the Israelites, when they saw the man, fled, etc. For a...",
          "anchorVerse": 24
        }
      ]
    },
    {
      "id": "provision",
      "label": "Provision",
      "color": "#d97706",
      "tier": "Strong",
      "summary": "This chapter emphasizes God’s supplying care, nourishment, sufficiency, or generous provision. Local Strong’s word study and cross references data reinforce this reading across 2 verses. Commentary leans on \"Bede on Commentary on Samuel: Therefore David left the vessels he had brought, etc. The Lord,...\". Word-study detail reinforces \"לֶ֖חֶם: loaves - food (for man or beast), especially bread, or grain (for making it)\".",
      "supportingVerses": [
        17,
        22
      ],
      "versePhrases": {
        "17": [
          "bread"
        ],
        "22": [
          "supplies"
        ]
      },
      "evidenceTrail": [
        {
          "kind": "strongs",
          "label": "Verse 17 word study",
          "detail": "לֶ֖חֶם: loaves - food (for man or beast), especially bread, or grain (for making it)",
          "anchorVerse": 17
        },
        {
          "kind": "historical_commentary",
          "label": "Verse 22 historical",
          "detail": "Bede on Commentary on Samuel: Therefore David left the vessels he had brought, etc. The Lord,...",
          "anchorVerse": 22
        }
      ]
    }
  ]
}
